pybammsolvers/version.py
pybammsolvers/idaklu.cpp
pybammsolvers/__init__.py
pybammsolvers/idaklu.cpython-313-darwin.so
pybammsolvers/.dylibs/libcasadi.3.7.dylib
pybammsolvers/.dylibs/libsundials_sunlinsollapackdense.5.3.0.dylib
pybammsolvers/.dylibs/libsundials_sunmatrixdense.5.3.0.dylib
pybammsolvers/.dylibs/libsundials_core.7.3.0.dylib
pybammsolvers/.dylibs/libsundials_sunmatrixsparse.5.3.0.dylib
pybammsolvers/.dylibs/libsuitesparseconfig.7.8.3.dylib
pybammsolvers/.dylibs/libc++.1.0.dylib
pybammsolvers/.dylibs/libsundials_sunlinsolklu.5.3.0.dylib
pybammsolvers/.dylibs/libklu.2.3.5.dylib
pybammsolvers/.dylibs/libbtf.2.3.2.dylib
pybammsolvers/.dylibs/libomp.dylib
pybammsolvers/.dylibs/libcolamd.3.3.4.dylib
pybammsolvers/.dylibs/libamd.3.3.3.dylib
pybammsolvers/.dylibs/libsundials_nvecserial.7.3.0.dylib
pybammsolvers/.dylibs/libsundials_sunlinsolspbcgs.5.3.0.dylib
pybammsolvers/.dylibs/libsundials_idas.6.3.0.dylib
pybammsolvers/.dylibs/libsundials_sunlinsoldense.5.3.0.dylib
pybammsolvers/.dylibs/libsundials_nvecopenmp.7.3.0.dylib
pybammsolvers/idaklu_source/IdakluJax.cpp
pybammsolvers/idaklu_source/common.cpp
pybammsolvers/idaklu_source/IDAKLUSolverOpenMP.hpp
pybammsolvers/idaklu_source/IDAKLUSolver.cpp
pybammsolvers/idaklu_source/sundials_functions.hpp
pybammsolvers/idaklu_source/idaklu_solver.hpp
pybammsolvers/idaklu_source/Solution.cpp
pybammsolvers/idaklu_source/IDAKLUSolverGroup.hpp
pybammsolvers/idaklu_source/IDAKLUSolverOpenMP_solvers.cpp
pybammsolvers/idaklu_source/sundials_functions.inl
pybammsolvers/idaklu_source/Options.cpp
pybammsolvers/idaklu_source/observe.hpp
pybammsolvers/idaklu_source/IDAKLUSolverOpenMP.inl
pybammsolvers/idaklu_source/SolutionData.cpp
pybammsolvers/idaklu_source/IDAKLUSolverOpenMP_solvers.hpp
pybammsolvers/idaklu_source/IDAKLUSolverGroup.cpp
pybammsolvers/idaklu_source/Options.hpp
pybammsolvers/idaklu_source/observe.cpp
pybammsolvers/idaklu_source/SolutionData.hpp
pybammsolvers-0.3.1.dist-info/RECORD
pybammsolvers-0.3.1.dist-info/WHEEL
pybammsolvers-0.3.1.dist-info/top_level.txt
pybammsolvers-0.3.1.dist-info/METADATA
pybammsolvers-0.3.1.dist-info/licenses/LICENSE
