Metadata-Version: 2.4
Name: pybammsolvers
Version: 0.3.1
Summary: Python interface for the IDAKLU solver
Requires-Python: <3.14,>=3.10
License-File: LICENSE
Requires-Dist: casadi==3.6.7
Requires-Dist: numpy
Provides-Extra: dev
Requires-Dist: pytest; extra == "dev"
Requires-Dist: setuptools; extra == "dev"
Requires-Dist: wheel; extra == "dev"
Dynamic: license-file
